nlevoconn/__init__.py
nlevoconn/docker.py
nlevoconn/rabbitmq.py
nlevoconn/rabbitmq_config.py
nlevoutils/__init__.py
nlevoutils/common.py
nlevoutils/constant.py
nlevoutils/default.py
nlevoutils/docker.py
nlevoutils/exceptions.py
nlevoutils/log_organizer.py
nlevoutils/multi_process.py
nlevoutils/subprocess.py
nlevoutils/timezone.py
nlevo-0.0.15.dist-info/LICENSE.txt
nlevo-0.0.15.dist-info/METADATA
nlevo-0.0.15.dist-info/WHEEL
nlevo-0.0.15.dist-info/top_level.txt
nlevo-0.0.15.dist-info/RECORD
