Metadata-Version: 2.1
Name: nlevo
Version: 0.0.15
Summary: Common library for evo.B
Author: nextlab
Author-email: swhan@nextlab.co.kr
Classifier: Programming Language :: Python :: 3
Classifier: License :: OSI Approved :: MIT License
Classifier: Operating System :: OS Independent
Requires-Python: >=3.8
License-File: LICENSE.txt
